MANIFEST.in
README.txt
setup.cfg
setup.py
Products/__init__.py
Products.ZOpenArchives.egg-info/PKG-INFO
Products.ZOpenArchives.egg-info/SOURCES.txt
Products.ZOpenArchives.egg-info/dependency_links.txt
Products.ZOpenArchives.egg-info/entry_points.txt
Products.ZOpenArchives.egg-info/namespace_packages.txt
Products.ZOpenArchives.egg-info/not-zip-safe
Products.ZOpenArchives.egg-info/paster_plugins.txt
Products.ZOpenArchives.egg-info/requires.txt
Products.ZOpenArchives.egg-info/top_level.txt
Products/ZOpenArchives/LICENSE.txt
Products/ZOpenArchives/MetadataAware.py
Products/ZOpenArchives/VERSION.txt
Products/ZOpenArchives/XMLStructure_config.py
Products/ZOpenArchives/ZCatalogHarvester.py
Products/ZOpenArchives/ZCatalogHarvester4eXist.py
Products/ZOpenArchives/ZopeOAIServer.py
Products/ZOpenArchives/__init__.py
Products/ZOpenArchives/configure.zcml
Products/ZOpenArchives/testOAI.xml
Products/ZOpenArchives/tests.py
Products/ZOpenArchives/utils.py
Products/ZOpenArchives/zOAIAggregator.py
Products/ZOpenArchives/zOAIExistAggregator.py
Products/ZOpenArchives/zOAIExistHarvester.py
Products/ZOpenArchives/zOAIExistNamespace.py
Products/ZOpenArchives/zOAIExistRepository.py
Products/ZOpenArchives/zOAIExistSet.py
Products/ZOpenArchives/zOAIExistSetRepository.py
Products/ZOpenArchives/zOAIExistTemplates.py
Products/ZOpenArchives/zOAIExistToken.py
Products/ZOpenArchives/zOAIHarvester.py
Products/ZOpenArchives/zOAINamespace.py
Products/ZOpenArchives/zOAIRecord.py
Products/ZOpenArchives/zOAIRepository.py
Products/ZOpenArchives/zOAISupport.py
Products/ZOpenArchives/zOAIToken.py
Products/ZOpenArchives/css/style_css.dtml
Products/ZOpenArchives/dtml/._manage_OAIExistNamespaceUpdateForm.dtml
Products/ZOpenArchives/dtml/._manage_addOAIExistNamespaceForm.dtml
Products/ZOpenArchives/dtml/advsearch_OAIRepositoryForm.dtml
Products/ZOpenArchives/dtml/manage_OAIAggregatorMainForm.dtml
Products/ZOpenArchives/dtml/manage_OAIAggregatorPrefsForm.dtml
Products/ZOpenArchives/dtml/manage_OAIExistAggregatorMainForm.dtml
Products/ZOpenArchives/dtml/manage_OAIExistAggregatorPrefsForm.dtml
Products/ZOpenArchives/dtml/manage_OAIExistNamespaceFiltersForm.dtml
Products/ZOpenArchives/dtml/manage_OAIExistNamespaceUpdateForm.dtml
Products/ZOpenArchives/dtml/manage_OAIExistRepositoryInfoForm.dtml
Products/ZOpenArchives/dtml/manage_OAIExistRepositoryMainForm.dtml
Products/ZOpenArchives/dtml/manage_OAIExistRepositorySetMainForm.dtml
