Metadata-Version: 1.1
Name: Products.ZOpenArchives
Version: 1.7.2
Summary: This product is an OAI implementation for the Zope server.
Home-page: http://svn.plone.org/svn/collective/
Author: UNIS (ENS Lyon)
Author-email: unis@ens-lyon.fr
License: GPL
Platform: UNKNOWN
Classifier: Framework :: Plone
Classifier: Programming Language :: Python
